recoverr/__init__.py
recoverr/result.py
recoverr-0.1.0.dist-info/METADATA
recoverr-0.1.0.dist-info/WHEEL
recoverr-0.1.0.dist-info/RECORD
