Metadata-Version: 2.1
Name: recoverr
Version: 0.1.0
Summary: 
Author: Tobias Egelund
Requires-Python: >=3.11,<4.0
Classifier: Programming Language :: Python :: 3
Classifier: Programming Language :: Python :: 3.11
Classifier: Programming Language :: Python :: 3.12
